{"name":"build-javascript","namedChunkGroups":{"app":{"name":"app","assets":[{"name":"webpack-runtime-bffb20e5787567c48bc8.js","size":3825},{"name":"styles.062b4a1f54e139fd1a37.css","size":7833},{"name":"app-69178e6efdad5fd3e566.js","size":225037}],"filteredAssets":0,"assetsSize":236695,"filteredAuxiliaryAssets":2,"auxiliaryAssetsSize":689690},"component---src-pages-404-jsx":{"name":"component---src-pages-404-jsx","assets":[{"name":"component---src-pages-404-jsx-9d91c020fae3947efa99.js","size":763}],"filteredAssets":0,"assetsSize":763,"filteredAuxiliaryAssets":1,"auxiliaryAssetsSize":1855},"component---src-pages-index-jsx":{"name":"component---src-pages-index-jsx","assets":[{"name":"component---src-pages-index-jsx-6756a979a4ed69307efb.js","size":40760}],"filteredAssets":0,"assetsSize":40760,"filteredAuxiliaryAssets":1,"auxiliaryAssetsSize":114045}},"assetsByChunkName":{"app":["webpack-runtime-bffb20e5787567c48bc8.js","styles.062b4a1f54e139fd1a37.css","app-69178e6efdad5fd3e566.js"],"component---src-pages-404-jsx":["component---src-pages-404-jsx-9d91c020fae3947efa99.js"],"component---src-pages-index-jsx":["component---src-pages-index-jsx-6756a979a4ed69307efb.js"]},"childAssetsByChunkName":{}}